Metadata-Version: 2.4
Name: aitop
Version: 0.11.0
Summary: A system monitor focused on AI/ML workload monitoring
Home-page: https://gitlab.com/CochainComplex/aitop
Author: Alexander Warth
Author-email: alexander.warth@mailbox.org
Project-URL: Homepage, https://gitlab.com/CochainComplex/aitop
Project-URL: Source, https://gitlab.com/CochainComplex/aitop
Project-URL: Bug Tracker, https://gitlab.com/CochainComplex/aitop/-/issues
Project-URL: Author Website, https://warth.ai
Classifier: Development Status :: 4 - Beta
Classifier: Environment :: Console :: Curses
Classifier: Intended Audience :: Developers
Classifier: Intended Audience :: System Administrators
Classifier: License :: OSI Approved :: MIT License
Classifier: Operating System :: POSIX :: Linux
Classifier: Programming Language :: Python :: 3
Classifier: Programming Language :: Python :: 3.9
Classifier: Programming Language :: Python :: 3.10
Classifier: Programming Language :: Python :: 3.11
Classifier: Topic :: System :: Monitoring
Requires-Python: >=3.9
License-File: LICENSE
Requires-Dist: psutil<6.0.0,>=5.9.0
Provides-Extra: dev
Requires-Dist: black<24.0.0,>=23.0.0; extra == "dev"
Requires-Dist: mypy<2.0.0,>=1.0.0; extra == "dev"
Requires-Dist: pytest<8.0.0,>=7.0.0; extra == "dev"
Requires-Dist: pytest-cov<5.0.0,>=4.1.0; extra == "dev"
Requires-Dist: pylint<3.0.0,>=2.17.0; extra == "dev"
Requires-Dist: isort<6.0.0,>=5.12.0; extra == "dev"
Requires-Dist: flake8<7.0.0,>=6.1.0; extra == "dev"
Requires-Dist: pre-commit<4.0.0,>=3.3.0; extra == "dev"
Requires-Dist: types-psutil<8.0.0,>=5.9.0; extra == "dev"
Provides-Extra: docs
Requires-Dist: sphinx<8.0.0,>=7.0.0; extra == "docs"
Requires-Dist: sphinx-rtd-theme<2.0.0,>=1.3.0; extra == "docs"
Dynamic: author
Dynamic: author-email
Dynamic: classifier
Dynamic: description
Dynamic: description-content-type
Dynamic: home-page
Dynamic: license-file
Dynamic: project-url
Dynamic: provides-extra
Dynamic: requires-dist
Dynamic: requires-python
Dynamic: summary
